Kregistrar/__init__.py
Kregistrar-0.0.1.dist-info/DESCRIPTION.rst
Kregistrar-0.0.1.dist-info/METADATA
Kregistrar-0.0.1.dist-info/RECORD
Kregistrar-0.0.1.dist-info/WHEEL
Kregistrar-0.0.1.dist-info/metadata.json
Kregistrar-0.0.1.dist-info/top_level.txt
